{
  "main": {
    "id": "4f4ba0dcce0108a0",
    "type": "split",
    "children": [
      {
        "id": "4823cc708bad1198",
        "type": "tabs",
        "children": [
          {
            "id": "2ed9315d06d66207",
            "type": "leaf",
            "state": {
              "type": "markdown",
              "state": {
                "file": "Reverse Engineering/5 - Step Plan.md",
                "mode": "source",
                "source": false,
                "backlinks": true,
                "backlinkOpts": {
                  "collapseAll": false,
                  "extraContext": false,
                  "sortOrder": "alphabetical",
                  "showSearch": false,
                  "searchQuery": "",
                  "backlinkCollapsed": false,
                  "unlinkedCollapsed": true
                }
              },
              "icon": "lucide-file",
              "title": "5 - Step Plan"
            }
          },
          {
            "id": "c92a3ca7ad28c4a7",
            "type": "leaf",
            "state": {
              "type": "markdown",
              "state": {
                "file": "objdump Command - RE.md",
                "mode": "source",
                "source": false,
                "backlinks": true,
                "backlinkOpts": {
                  "collapseAll": false,
                  "extraContext": false,
                  "sortOrder": "alphabetical",
                  "showSearch": false,
                  "searchQuery": "",
                  "backlinkCollapsed": false,
                  "unlinkedCollapsed": true
                }
              },
              "icon": "lucide-file",
              "title": "objdump Command - RE"
            }
          }
        ],
        "currentTab": 1
      }
    ],
    "direction": "vertical"
  },
  "left": {
    "id": "41ada77f9c7810e0",
    "type": "split",
    "children": [
      {
        "id": "90f2efb3405eef97",
        "type": "tabs",
        "dimension": 76.9170579029734,
        "children": [
          {
            "id": "7ff640d71c0bd486",
            "type": "leaf",
            "state": {
              "type": "file-explorer",
              "state": {
                "sortOrder": "alphabetical",
                "autoReveal": false
              },
              "icon": "lucide-folder-closed",
              "title": "Files"
            }
          },
          {
            "id": "c2b0c40c7e69c190",
            "type": "leaf",
            "state": {
              "type": "bookmarks",
              "state": {},
              "icon": "lucide-bookmark",
              "title": "Bookmarks"
            }
          }
        ]
      },
      {
        "id": "1e8e174aae067a25",
        "type": "tabs",
        "dimension": 23.082942097026603,
        "children": [
          {
            "id": "23551fd757c41ab1",
            "type": "leaf",
            "state": {
              "type": "graph",
              "state": {},
              "icon": "lucide-git-fork",
              "title": "Graph view"
            }
          }
        ]
      }
    ],
    "direction": "horizontal",
    "width": 486.5
  },
  "right": {
    "id": "9afd9f5eac9b497f",
    "type": "split",
    "children": [
      {
        "id": "9feef465bbcd33cf",
        "type": "tabs",
        "dimension": 55.9953434225844,
        "children": [
          {
            "id": "1579869d6db8b018",
            "type": "leaf",
            "state": {
              "type": "backlink",
              "state": {
                "collapseAll": false,
                "extraContext": false,
                "sortOrder": "alphabetical",
                "showSearch": false,
                "searchQuery": "",
                "backlinkCollapsed": false,
                "unlinkedCollapsed": true
              },
              "icon": "links-coming-in",
              "title": "Backlinks"
            }
          },
          {
            "id": "f5647a7b513f54c3",
            "type": "leaf",
            "state": {
              "type": "outgoing-link",
              "state": {
                "linksCollapsed": false,
                "unlinkedCollapsed": true
              },
              "icon": "links-going-out",
              "title": "Outgoing links"
            }
          },
          {
            "id": "30b36ad283bd356f",
            "type": "leaf",
            "state": {
              "type": "tag",
              "state": {
                "sortOrder": "alphabetical",
                "useHierarchy": false,
                "showSearch": false,
                "searchQuery": ""
              },
              "icon": "lucide-tags",
              "title": "Tags"
            }
          },
          {
            "id": "d147a4afce0574ec",
            "type": "leaf",
            "state": {
              "type": "outline",
              "state": {
                "followCursor": false,
                "showSearch": false,
                "searchQuery": ""
              },
              "icon": "lucide-list",
              "title": "Outline"
            }
          }
        ],
        "currentTab": 2
      },
      {
        "id": "7cdabd26ade909dc",
        "type": "tabs",
        "dimension": 44.0046565774156,
        "children": [
          {
            "id": "3f1ff2d13d23690f",
            "type": "leaf",
            "state": {
              "type": "calendar",
              "state": {},
              "icon": "calendar-with-checkmark",
              "title": "Calendar"
            }
          }
        ]
      }
    ],
    "direction": "horizontal",
    "width": 450.5,
    "collapsed": true
  },
  "left-ribbon": {
    "hiddenItems": {
      "switcher:Open quick switcher": false,
      "graph:Open graph view": false,
      "canvas:Create new canvas": false,
      "daily-notes:Open today's daily note": false,
      "templates:Insert template": false,
      "command-palette:Open command palette": false,
      "bases:Create new base": false,
      "templater-obsidian:Templater": false,
      "omnisearch:Omnisearch": false,
      "obsidian-git:Open Git source control": false
    }
  },
  "active": "c92a3ca7ad28c4a7",
  "lastOpenFiles": [
    "Terminal Commands/Overall usefull Commands.md",
    "objdump Command - RE.md",
    "Strings Command - RE.md",
    "Hex Dump & Reverse Hex Dump.md",
    "Reverse Engineering/5 - Step Plan.md",
    "000 Index/Tags/%Command.md",
    "Terminal Commands",
    "000 Index/Tags/%Reverse Engineering.md",
    "000 Index/Tags/%UI.md",
    "000 Index/Tags/%Binary.md",
    "000 Index/Tags/%LowLevel.md",
    "000 Index/Tags/%Cyber Security.md",
    "500 Philosophie/Books/Schönes Leben/Exkursion in die Philosophie - Edward Hopper.md",
    "Reverse Engineering",
    "200 CS/Languages/C/Structs - C/Initializing Structs - C.md",
    "200 CS/Languages/C/Structs - C/Basic Structs - C.md",
    "200 CS/Languages/C/Basics - C/Functions & Loops - C.md",
    "200 CS/Languages/C/Basics - C/Enums - C.md",
    "100 Obsidian/Obsidian Setup.md",
    "200 CS/Coding Things/Web UI Templates/Daisy.md",
    "200 CS/Coding Things/Web UI Templates/Flowbite.md",
    "200 CS/Coding Things/Web UI Templates/Shadcn.md",
    "200 CS/Coding Things/Web UI Templates/Tailwind.md",
    "800 Other/Fallbeispiele für den Tag der offenen Tür.md",
    "000 Index/Tags/%ShortStory.md",
    "750 Writing/English/Short Story/What makes a good Short Story?.md",
    "000 Index/Tags/%English.md",
    "600 Debate/Politics/Das Haus der Migration.md",
    "200 CS/Languages/C/Pointer - C",
    "200 CS/Languages/C/Basics - C",
    "200 CS/Languages/C/Structs - C",
    "200 CS/CS Projects/Low Level",
    "200 CS/CS Projects/Hardware",
    "200 CS/CS Projects/Web",
    "200 CS/Hardware",
    "200 CS/Languages",
    "Pasted image 20251113203103.png",
    "Untitled.canvas"
  ]
}